{
    "name": "null",
    "alternateNames": [
      "layout",
      "routing"
    ],
    "defaultNodeName": "",
    "path": [
      "geometry"
    ],
    "input": {
      "geometry": {
        "type": "geometry",
        "displayName": "geometry"
      }
    },
    "type": "Null",
    "output": {
      "geometry": {
        "type": "geometry",
        "displayName": "geometry"
      },
      "points": {
        "type": "list:vector",
        "displayName": "points"
      },
      "points.x": {
        "type": "list:float",
        "displayName": "points.x"
      },
      "points.y": {
        "type": "list:float",
        "displayName": "points.y"
      },
      "points.z": {
        "type": "list:float",
        "displayName": "points.z"
      }
    },
    "nodeClass": "node"
}