{
    "name": "box",
    "alternateNames": [
      "cube",
      "poly box"
    ],
    "defaultNodeName": "box",
    "path": [
      "geometry",
      "create"
    ],
    "input": {
      "mode": {
        "type": "enum",
        "options": [
          "normal",
          "CSG"
        ],
        "displayName": "type"
      },
      "center": {
        "type": "flexi:vector",
        "default": [
          0,
          0,
          0
        ],
        "displayName": "center"
      },
      "scale": {
        "type": "flexi:vector",
        "default": [
          1,
          1,
          1
        ],
        "displayName": "scale"
      },
      "uniformScale": {
        "type": "flexi:float",
        "default": 1000,
        "displayName": "uniform scale"
      }
    },
    "type": "PolyBox",
    "output": {
      "geometry": {
        "type": "geometry",
        "displayName": "geometry"
      },
      "points": {
        "type": "list:vector",
        "displayName": "points"
      },
      "points.x": {
        "type": "list:float",
        "displayName": "points.x"
      },
      "points.y": {
        "type": "list:float",
        "displayName": "points.y"
      },
      "points.z": {
        "type": "list:float",
        "displayName": "points.z"
      }
    },
    "nodeClass": "node"
  }