{
    "name": "arc cosine",
    "alternateNames": [
      "acos",
      "arc cosinus"
    ],
    "defaultNodeName": "arc cosine",
    "path": [
      "math",
      "trigonometry"
    ],
    "help": "Performs an arc cosine function on a value.",
    "input": {
      "value": {
        "type": "flexi:float",
        "default": 0,
        "displayName": "value"
      }
    },
    "type": "Acos",
    "output": {
      "result": {
        "type": "float",
        "displayName": "result"
      },
      "result list": {
        "type": "list:float",
        "displayName": "result list"
      }
    },
    "nodeClass": "math"
  }